aibread/__init__.py
aibread/_base_client.py
aibread/_client.py
aibread/_compat.py
aibread/_constants.py
aibread/_exceptions.py
aibread/_files.py
aibread/_models.py
aibread/_qs.py
aibread/_resource.py
aibread/_response.py
aibread/_streaming.py
aibread/_types.py
aibread/_version.py
aibread/py.typed
aibread/_utils/__init__.py
aibread/_utils/_compat.py
aibread/_utils/_datetime_parse.py
aibread/_utils/_logs.py
aibread/_utils/_proxy.py
aibread/_utils/_reflection.py
aibread/_utils/_resources_proxy.py
aibread/_utils/_streams.py
aibread/_utils/_sync.py
aibread/_utils/_transform.py
aibread/_utils/_typing.py
aibread/_utils/_utils.py
aibread/lib/.keep
aibread/resources/__init__.py
aibread/resources/bakes.py
aibread/resources/health.py
aibread/resources/prompts.py
aibread/resources/recipes.py
aibread/resources/repo.py
aibread/resources/targets/__init__.py
aibread/resources/targets/rollout.py
aibread/resources/targets/stim.py
aibread/resources/targets/targets.py
aibread/types/__init__.py
aibread/types/bake_batch_set_params.py
aibread/types/bake_batch_set_response.py
aibread/types/bake_config_base_param.py
aibread/types/bake_create_batch_params.py
aibread/types/bake_create_batch_response.py
aibread/types/bake_create_params.py
aibread/types/bake_delete_params.py
aibread/types/bake_download_params.py
aibread/types/bake_download_response.py
aibread/types/bake_get_metrics_params.py
aibread/types/bake_get_metrics_response.py
aibread/types/bake_get_params.py
aibread/types/bake_list_params.py
aibread/types/bake_list_response.py
aibread/types/bake_response.py
aibread/types/bake_run_params.py
aibread/types/bake_set_params.py
aibread/types/checkpoint_config_param.py
aibread/types/data_config_param.py
aibread/types/data_source_param.py
aibread/types/dataset_item_param.py
aibread/types/deepspeed_config_param.py
aibread/types/delete_response.py
aibread/types/generator.py
aibread/types/generator_param.py
aibread/types/health_check_response.py
aibread/types/message.py
aibread-1.4.0.dist-info/METADATA
aibread-1.4.0.dist-info/WHEEL
aibread-1.4.0.dist-info/licenses/LICENSE
aibread-1.4.0.dist-info/RECORD
